llama_index/graph_stores/kuzu/__init__.py
llama_index/graph_stores/kuzu/base.py
llama_index/graph_stores/kuzu/kuzu_property_graph.py
llama_index/graph_stores/kuzu/utils.py
llama_index_graph_stores_kuzu-0.9.1.dist-info/METADATA
llama_index_graph_stores_kuzu-0.9.1.dist-info/WHEEL
llama_index_graph_stores_kuzu-0.9.1.dist-info/licenses/LICENSE
llama_index_graph_stores_kuzu-0.9.1.dist-info/RECORD
