Metadata-Version: 2.4
Name: llama-index-graph-stores-kuzu
Version: 0.9.1
Summary: llama-index graph stores kuzu integration
Author-email: Your Name <you@example.com>
License-Expression: MIT
License-File: LICENSE
Requires-Python: <4.0,>=3.9
Requires-Dist: kuzu<0.12,>=0.11.0
Requires-Dist: llama-index-core<0.15,>=0.13.0
